README.md
setup.py
pydream_rocket/__init__.py
pydream_rocket/server.py
pydream_rocket.egg-info/PKG-INFO
pydream_rocket.egg-info/SOURCES.txt
pydream_rocket.egg-info/dependency_links.txt
pydream_rocket.egg-info/not-zip-safe
pydream_rocket.egg-info/requires.txt
pydream_rocket.egg-info/top_level.txt