Metadata-Version: 1.1
Name: pydream-rocket
Version: 0.2.0
Summary: Control DreamCheeky USB rocket launchers
Home-page: https://github.com/BasementCat/pydream-rocket
Author: Alec Elton
Author-email: alec.elton@gmail.com
License: UNKNOWN
Platform: UNKNOWN
Classifier: Development Status :: 3 - Alpha
Classifier: Intended Audience :: Developers
Classifier: License :: Other/Proprietary License
Classifier: Natural Language :: English
Classifier: Operating System :: OS Independent
Classifier: Programming Language :: Python :: 2
